acme_client/__init__.py
acme_client/_client.py
acme_client/_rsa_utils.py
acme_client/_schemas.py
acme_client_lib-0.1.1.dist-info/LICENSE
acme_client_lib-0.1.1.dist-info/METADATA
acme_client_lib-0.1.1.dist-info/WHEEL
acme_client_lib-0.1.1.dist-info/RECORD
