Metadata-Version: 2.3
Name: acme-client-lib
Version: 0.1.1
Summary: Asynchronous ACME client
License: MIT
Author: Aleksey Matyunin
Author-email: matyunin.as@mail.ru
Requires-Python: >=3.9,<4.0
Classifier: License :: OSI Approved :: MIT License
Classifier: Programming Language :: Python :: 3
Classifier: Programming Language :: Python :: 3.9
Classifier: Programming Language :: Python :: 3.10
Classifier: Programming Language :: Python :: 3.11
Classifier: Programming Language :: Python :: 3.12
Classifier: Programming Language :: Python :: 3.13
Requires-Dist: async-client-lib (>=0.1.8,<0.2.0)
Requires-Dist: cryptography (>=42.0.1,<43.0.0)
Requires-Dist: josepy (>=1.14.0,<2.0.0)
